bollm/__init__.py
bollm/apollo.py
bollm/azure.py
bollm/billo.py
bollm/config.py
bollm/pandasai.py
bollm/parse_docs.py
bollm/utils.py
tests/__init__.py
tests/test_azure.py
tests/test_billo.py
tests/test_pandasai.py
tests/test_parse_docs.py
bollm-0.1.1.dist-info/LICENSE
bollm-0.1.1.dist-info/METADATA
bollm-0.1.1.dist-info/WHEEL
bollm-0.1.1.dist-info/top_level.txt
bollm-0.1.1.dist-info/RECORD
