Metadata-Version: 2.1
Name: bollm
Version: 0.1.1
Summary: Framework for building LLM-based apps in Boehringer Ingelheim
Home-page: https://bitbucket.biscrum.com/projects/MAGIC/repos/billm/browse
Author: Steven Brooks
Author-email: steven.brooks@boehringer.com
Classifier: Programming Language :: Python :: 3
Classifier: License :: OSI Approved :: MIT License
Classifier: Operating System :: OS Independent
Requires-Python: >=3.9
License-File: LICENSE
Requires-Dist: streamlit ==1.31.0
Requires-Dist: python-dotenv ==1.0.1
Requires-Dist: requests ==2.31.0
Requires-Dist: langchain ==0.2.5
Requires-Dist: langchain-community ==0.2.5
Requires-Dist: unstructured ==0.13.2
Requires-Dist: openai ==1.34.0
Requires-Dist: retrying ==1.3.4
Requires-Dist: oauthlib ==3.2.2
Requires-Dist: requests-oauthlib ==2.0.0
